nist/__init__.py
nist/_modidx.py
nist/atyp.py
nist/cons.py
nist/docs.py
nist/errs.py
nist/fact.py
nist/unit.py
nist/util.py
nist-0.0.3.dist-info/LICENSE
nist-0.0.3.dist-info/METADATA
nist-0.0.3.dist-info/WHEEL
nist-0.0.3.dist-info/entry_points.txt
nist-0.0.3.dist-info/top_level.txt
nist-0.0.3.dist-info/RECORD
