Metadata-Version: 2.1
Name: nist
Version: 0.0.3
Summary: si type metric
Home-page: https://github.com/dsm-72/nist
Author: dsm-72
Author-email: sumner.magruder@yale.edu
License: Apache Software License 2.0
Keywords: nbdev jupyter notebook python byte bytes kilo tera giga unit dataclass strenum
Classifier: Development Status :: 4 - Beta
Classifier: Intended Audience :: Developers
Classifier: Natural Language :: English
Classifier: Programming Language :: Python :: 3.11
Classifier: License :: OSI Approved :: Apache Software License
Requires-Python: >=3.11
License-File: LICENSE
Requires-Dist: atyp
Requires-Dist: regsyn
Requires-Dist: ispec
Requires-Dist: pstr
Requires-Dist: sint
Requires-Dist: pfmt
Requires-Dist: nchr
Requires-Dist: nlit
Provides-Extra: dev
